Neostate/__init__.py
Neostate/center.py
Neostate/cli.py
Neostate/futurebuilder.py
Neostate/mypage.py
Neostate/router.py
Neostate/state_manager.py
Neostate-0.1.5.dist-info/LICENSE
Neostate-0.1.5.dist-info/METADATA
Neostate-0.1.5.dist-info/WHEEL
Neostate-0.1.5.dist-info/entry_points.txt
Neostate-0.1.5.dist-info/top_level.txt
Neostate-0.1.5.dist-info/RECORD
