Metadata-Version: 2.2
Name: Neostate
Version: 0.1.5
Summary: Welcome to Neostate! 🌈 A lightweight and intuitive library for managing shared states in Flet applications. With StateCraft, you can bind widgets to a shared state effortlessly, enabling seamless updates across your UI components with minimal boilerplate.
Home-page: https://github.com/dekuChaurasia/Neostate
Author: Deku Chaurasia
Author-email: angryg575@gmail.com
Classifier: Programming Language :: Python :: 3
Classifier: License :: OSI Approved :: MIT License
Classifier: Operating System :: OS Independent
Requires-Python: >=3.6
License-File: LICENSE
Requires-Dist: flet
Requires-Dist: requests
Dynamic: author
Dynamic: author-email
Dynamic: classifier
Dynamic: description
Dynamic: description-content-type
Dynamic: home-page
Dynamic: requires-dist
Dynamic: requires-python
Dynamic: summary
